meld3/__init__.py
meld3/_compat.py
meld3/meld3.py
meld3/test_meld3.py
meld3-2.0.0.dist-info/LICENSE.txt
meld3-2.0.0.dist-info/METADATA
meld3-2.0.0.dist-info/WHEEL
meld3-2.0.0.dist-info/top_level.txt
meld3-2.0.0.dist-info/RECORD
