Metadata-Version: 1.2
Name: meld3
Version: 2.0.0
Summary: meld3 is an HTML/XML templating engine.
Home-page: https://github.com/supervisor/meld3
Author: Chris McDonough
Author-email: chrism@plope.com
Maintainer: Chris McDonough
Maintainer-email: chrism@plope.com
License: BSD-derived (http://www.repoze.org/LICENSE.txt)
Platform: UNKNOWN
Classifier: Development Status :: 5 - Production/Stable
Classifier: Environment :: Web Environment
Classifier: Intended Audience :: Developers
Classifier: Operating System :: POSIX
Classifier: Programming Language :: Python :: 2
Classifier: Programming Language :: Python :: 2.7
Classifier: Programming Language :: Python :: 3
Classifier: Programming Language :: Python :: 3.4
Classifier: Programming Language :: Python :: 3.5
Classifier: Programming Language :: Python :: 3.6
Classifier: Programming Language :: Python :: 3.7
Classifier: Topic :: Text Processing :: Markup :: HTML
